README.md
setup.py
ShapeY.egg-info/PKG-INFO
ShapeY.egg-info/SOURCES.txt
ShapeY.egg-info/dependency_links.txt
ShapeY.egg-info/requires.txt
ShapeY.egg-info/top_level.txt
shapey/__init__.py
shapey/dataprocess/__init__.py
shapey/dataprocess/raw_data.py
shapey/utils/__init__.py
shapey/utils/configs.py
shapey/utils/customdataset.py
shapey/utils/customfunc.py
shapey/utils/datasaver.py
shapey/utils/macroutils.py
shapey/utils/modelutils.py
shapey/visualization/__init__.py
shapey/visualization/correlation_fall_off.py
shapey/visualization/exclusion_distance.py
shapey/visualization/histogram.py
shapey/visualization/image_panel.py